[
    {
        "date": "2025-06-30",
        "symbol": "CPAY",
        "reportedCurrency": "USD",
        "cik": "0001175454",
        "fillingDate": "2025-08-07",
        "acceptedDate": "2025-08-07 08:55:55",
        "calendarYear": "2025",
        "period": "Q2",
        "netIncome": 284078000,
        "depreciationAndAmortization": 91350000,
        "deferredIncomeTax": -17516000,
        "stockBasedCompensation": 28868000,
        "changeInWorkingCapital": 728052000,
        "accountsReceivables": -174712000,
        "inventory": 0,
        "accountsPayables": 0,
        "otherWorkingCapital": 902764000,
        "otherNonCashItems": 25415000,
        "netCashProvidedByOperatingActivities": 1140247000,
        "investmentsInPropertyPlantAndEquipment": -52636000,
        "acquisitionsNet": -929000,
        "purchasesOfInvestments": 0,
        "salesMaturitiesOfInvestments": 14843000,
        "otherInvestingActivites": 0,
        "netCashUsedForInvestingActivites": -38722000,
        "debtRepayment": -56285000,
        "commonStockIssued": 23883000,
        "commonStockRepurchased": -32159000,
        "dividendsPaid": 0,
        "otherFinancingActivites": 619000,
        "netCashUsedProvidedByFinancingActivities": -63942000,
        "effectOfForexChangesOnCash": 110352000,
        "netChangeInCash": 1147935000,
        "cashAtEndOfPeriod": 5531358000,
        "cashAtBeginningOfPeriod": 4383423000,
        "operatingCashFlow": 1140247000,
        "capitalExpenditure": -52636000,
        "freeCashFlow": 1087611000,
        "link": "https://www.sec.gov/Archives/edgar/data/1175454/000117545425000018/0001175454-25-000018-index.htm",
        "finalLink": "https://www.sec.gov/Archives/edgar/data/1175454/000117545425000018/cpay-20250630.htm"
    },
    {
        "date": "2025-03-31",
        "symbol": "CPAY",
        "reportedCurrency": "USD",
        "cik": "0001175454",
        "fillingDate": "2025-05-12",
        "acceptedDate": "2025-05-12 16:59:50",
        "calendarYear": "2025",
        "period": "Q1",
        "netIncome": 243875000,
        "depreciationAndAmortization": 92188000,
        "deferredIncomeTax": -7983000,
        "stockBasedCompensation": 18366000,
        "changeInWorkingCapital": -455082000,
        "accountsReceivables": -565649000,
        "inventory": 0,
        "accountsPayables": 126400000,
        "otherWorkingCapital": -15833000,
        "otherNonCashItems": 34485000,
        "netCashProvidedByOperatingActivities": -74151000,
        "investmentsInPropertyPlantAndEquipment": -44771000,
        "acquisitionsNet": -153719000,
        "purchasesOfInvestments": 0,
        "salesMaturitiesOfInvestments": 0,
        "otherInvestingActivites": 14572000,
        "netCashUsedForInvestingActivites": -183918000,
        "debtRepayment": 180715000,
        "commonStockIssued": 32079000,
        "commonStockRepurchased": -58718000,
        "dividendsPaid": 0,
        "otherFinancingActivites": -11779000,
        "netCashUsedProvidedByFinancingActivities": 142297000,
        "effectOfForexChangesOnCash": 42850000,
        "netChangeInCash": -72922000,
        "cashAtEndOfPeriod": 4383423000,
        "cashAtBeginningOfPeriod": 4456345000,
        "operatingCashFlow": -74151000,
        "capitalExpenditure": -44771000,
        "freeCashFlow": -118922000,
        "link": "https://www.sec.gov/Archives/edgar/data/1175454/000162828025024747/0001628280-25-024747-index.htm",
        "finalLink": "https://www.sec.gov/Archives/edgar/data/1175454/000162828025024747/cpay-20250331.htm"
    },
    {
        "date": "2024-12-31",
        "symbol": "CPAY",
        "reportedCurrency": "USD",
        "cik": "0001175454",
        "fillingDate": "2025-02-27",
        "acceptedDate": "2025-02-27 17:13:10",
        "calendarYear": "2024",
        "period": "Q4",
        "netIncome": 246004000,
        "depreciationAndAmortization": 92440000,
        "deferredIncomeTax": -45733000,
        "stockBasedCompensation": 36131000,
        "changeInWorkingCapital": 326994000,
        "accountsReceivables": 407718000,
        "inventory": 0,
        "accountsPayables": 0,
        "otherWorkingCapital": -80724000,
        "otherNonCashItems": -7164000,
        "netCashProvidedByOperatingActivities": 648672000,
        "investmentsInPropertyPlantAndEquipment": -44109000,
        "acquisitionsNet": -390699000,
        "purchasesOfInvestments": 0,
        "salesMaturitiesOfInvestments": 0,
        "otherInvestingActivites": 5570000,
        "netCashUsedForInvestingActivites": -429238000,
        "debtRepayment": 248575000,
        "commonStockIssued": 243556000,
        "commonStockRepurchased": -248750000,
        "dividendsPaid": 0,
        "otherFinancingActivites": -14628000,
        "netCashUsedProvidedByFinancingActivities": 228753000,
        "effectOfForexChangesOnCash": -146853000,
        "netChangeInCash": 301334000,
        "cashAtEndOfPeriod": 4456345000,
        "cashAtBeginningOfPeriod": 4155011000,
        "operatingCashFlow": 648672000,
        "capitalExpenditure": -44109000,
        "freeCashFlow": 604563000,
        "link": "https://www.sec.gov/Archives/edgar/data/1175454/000162828025008746/0001628280-25-008746-index.htm",
        "finalLink": "https://www.sec.gov/Archives/edgar/data/1175454/000162828025008746/flt-20241231.htm"
    },
    {
        "date": "2024-09-30",
        "symbol": "CPAY",
        "reportedCurrency": "USD",
        "cik": "0001175454",
        "fillingDate": "2024-11-08",
        "acceptedDate": "2024-11-08 08:24:00",
        "calendarYear": "2024",
        "period": "Q3",
        "netIncome": 276262000,
        "depreciationAndAmortization": 89546000,
        "deferredIncomeTax": -9310000,
        "stockBasedCompensation": 28506000,
        "changeInWorkingCapital": -19602000,
        "accountsReceivables": -87365000,
        "inventory": 0,
        "accountsPayables": 0,
        "otherWorkingCapital": 67763000,
        "otherNonCashItems": 35386000,
        "netCashProvidedByOperatingActivities": 400788000,
        "investmentsInPropertyPlantAndEquipment": -45778000,
        "acquisitionsNet": -185848000,
        "purchasesOfInvestments": 0,
        "salesMaturitiesOfInvestments": 0,
        "otherInvestingActivites": 0,
        "netCashUsedForInvestingActivites": -231626000,
        "debtRepayment": 408655000,
        "commonStockIssued": 84427000,
        "commonStockRepurchased": -92174000,
        "dividendsPaid": 0,
        "otherFinancingActivites": 14566000,
        "netCashUsedProvidedByFinancingActivities": 415474000,
        "effectOfForexChangesOnCash": 23079000,
        "netChangeInCash": 607715000,
        "cashAtEndOfPeriod": 4155011000,
        "cashAtBeginningOfPeriod": 3547296000,
        "operatingCashFlow": 400788000,
        "capitalExpenditure": -45778000,
        "freeCashFlow": 355010000,
        "link": "https://www.sec.gov/Archives/edgar/data/1175454/000162828024046515/0001628280-24-046515-index.htm",
        "finalLink": "https://www.sec.gov/Archives/edgar/data/1175454/000162828024046515/cpay-20240930.htm"
    },
    {
        "date": "2024-06-30",
        "symbol": "CPAY",
        "reportedCurrency": "USD",
        "cik": "0001175454",
        "fillingDate": "2024-08-09",
        "acceptedDate": "2024-08-09 14:36:57",
        "calendarYear": "2024",
        "period": "Q2",
        "netIncome": 251663000,
        "depreciationAndAmortization": 84342000,
        "deferredIncomeTax": -10322000,
        "stockBasedCompensation": 27108000,
        "changeInWorkingCapital": 157963000,
        "accountsReceivables": -114395000,
        "inventory": 0,
        "accountsPayables": 0,
        "otherWorkingCapital": 272358000,
        "otherNonCashItems": 30167000,
        "netCashProvidedByOperatingActivities": 540921000,
        "investmentsInPropertyPlantAndEquipment": -44096000,
        "acquisitionsNet": -3546000,
        "purchasesOfInvestments": 0,
        "salesMaturitiesOfInvestments": 0,
        "otherInvestingActivites": 3373000,
        "netCashUsedForInvestingActivites": -44269000,
        "debtRepayment": 566650000,
        "commonStockIssued": 9403000,
        "commonStockRepurchased": -658241000,
        "dividendsPaid": 0,
        "otherFinancingActivites": 1501000,
        "netCashUsedProvidedByFinancingActivities": -80687000,
        "effectOfForexChangesOnCash": -71345000,
        "netChangeInCash": 344620000,
        "cashAtEndOfPeriod": 3547296000,
        "cashAtBeginningOfPeriod": 3202676000,
        "operatingCashFlow": 540921000,
        "capitalExpenditure": -44096000,
        "freeCashFlow": 496825000,
        "link": "https://www.sec.gov/Archives/edgar/data/1175454/000162828024036429/0001628280-24-036429-index.htm",
        "finalLink": "https://www.sec.gov/Archives/edgar/data/1175454/000162828024036429/cpay-20240630.htm"
    },
    {
        "date": "2024-03-31",
        "symbol": "CPAY",
        "reportedCurrency": "USD",
        "cik": "0001175454",
        "fillingDate": "2024-03-31",
        "acceptedDate": "2024-03-29 20:00:00",
        "calendarYear": "2024",
        "period": "Q1",
        "netIncome": 229803000,
        "depreciationAndAmortization": 84760000,
        "deferredIncomeTax": 647000,
        "stockBasedCompensation": 24979000,
        "changeInWorkingCapital": -17501000,
        "accountsReceivables": -382889000,
        "inventory": 0,
        "accountsPayables": 398544000,
        "otherWorkingCapital": -33156000,
        "otherNonCashItems": 27496000,
        "netCashProvidedByOperatingActivities": 350184000,
        "investmentsInPropertyPlantAndEquipment": -41193000,
        "acquisitionsNet": -56325000,
        "purchasesOfInvestments": 0,
        "salesMaturitiesOfInvestments": 0,
        "otherInvestingActivites": -4826000,
        "netCashUsedForInvestingActivites": -102344000,
        "debtRepayment": 42040000,
        "commonStockIssued": 90838000,
        "commonStockRepurchased": -288833000,
        "dividendsPaid": 0,
        "otherFinancingActivites": -2596000,
        "netCashUsedProvidedByFinancingActivities": -158551000,
        "effectOfForexChangesOnCash": -28148000,
        "netChangeInCash": 61141000,
        "cashAtEndOfPeriod": 3202676000,
        "cashAtBeginningOfPeriod": 3141535000,
        "operatingCashFlow": 350184000,
        "capitalExpenditure": -41193000,
        "freeCashFlow": 308991000,
        "link": null,
        "finalLink": null
    },
    {
        "date": "2023-12-31",
        "symbol": "CPAY",
        "reportedCurrency": "USD",
        "cik": "0001175454",
        "fillingDate": "2023-12-31",
        "acceptedDate": "2023-12-30 19:00:00",
        "calendarYear": "2023",
        "period": "Q4",
        "netIncome": 255857000,
        "depreciationAndAmortization": 83946000,
        "deferredIncomeTax": -27767000,
        "stockBasedCompensation": 26169000,
        "changeInWorkingCapital": 835423000,
        "accountsReceivables": 599226000,
        "inventory": 0,
        "accountsPayables": 0,
        "otherWorkingCapital": 236197000,
        "otherNonCashItems": 23635000,
        "netCashProvidedByOperatingActivities": 1197263000,
        "investmentsInPropertyPlantAndEquipment": -36664000,
        "acquisitionsNet": 1587000,
        "purchasesOfInvestments": 0,
        "salesMaturitiesOfInvestments": 0,
        "otherInvestingActivites": 0,
        "netCashUsedForInvestingActivites": -35077000,
        "debtRepayment": -266655000,
        "commonStockIssued": 12540000,
        "commonStockRepurchased": -139949000,
        "dividendsPaid": 0,
        "otherFinancingActivites": -2688000,
        "netCashUsedProvidedByFinancingActivities": -396752000,
        "effectOfForexChangesOnCash": 60588000,
        "netChangeInCash": 826022000,
        "cashAtEndOfPeriod": 3141535000,
        "cashAtBeginningOfPeriod": 2315513000,
        "operatingCashFlow": 1197263000,
        "capitalExpenditure": -36664000,
        "freeCashFlow": 1160599000,
        "link": null,
        "finalLink": null
    },
    {
        "date": "2023-09-30",
        "symbol": "CPAY",
        "reportedCurrency": "USD",
        "cik": "0001175454",
        "fillingDate": "2023-09-30",
        "acceptedDate": "2023-09-29 20:00:00",
        "calendarYear": "2023",
        "period": "Q3",
        "netIncome": 271496000,
        "depreciationAndAmortization": 84750000,
        "deferredIncomeTax": -7112000,
        "stockBasedCompensation": 29073000,
        "changeInWorkingCapital": -108930000,
        "accountsReceivables": -377091000,
        "inventory": 0,
        "accountsPayables": 0,
        "otherWorkingCapital": 268161000,
        "otherNonCashItems": 16393000,
        "netCashProvidedByOperatingActivities": 285670000,
        "investmentsInPropertyPlantAndEquipment": -38236000,
        "acquisitionsNet": -106195000,
        "purchasesOfInvestments": 0,
        "salesMaturitiesOfInvestments": 0,
        "otherInvestingActivites": 0,
        "netCashUsedForInvestingActivites": -144431000,
        "debtRepayment": 240473000,
        "commonStockIssued": 35054000,
        "commonStockRepurchased": -534937000,
        "dividendsPaid": 0,
        "otherFinancingActivites": -238000,
        "netCashUsedProvidedByFinancingActivities": -259648000,
        "effectOfForexChangesOnCash": -68832000,
        "netChangeInCash": -187241000,
        "cashAtEndOfPeriod": 2796274000,
        "cashAtBeginningOfPeriod": 2983515000,
        "operatingCashFlow": 285670000,
        "capitalExpenditure": -38236000,
        "freeCashFlow": 247434000,
        "link": null,
        "finalLink": null
    },
    {
        "date": "2023-06-30",
        "symbol": "CPAY",
        "reportedCurrency": "USD",
        "cik": "0001175454",
        "fillingDate": "2023-06-30",
        "acceptedDate": "2023-06-29 20:00:00",
        "calendarYear": "2023",
        "period": "Q2",
        "netIncome": 239702000,
        "depreciationAndAmortization": 83676000,
        "deferredIncomeTax": -11300000,
        "stockBasedCompensation": 34748000,
        "changeInWorkingCapital": -163299000,
        "accountsReceivables": -728064000,
        "inventory": 0,
        "accountsPayables": 246531000,
        "otherWorkingCapital": 318234000,
        "otherNonCashItems": 37768000,
        "netCashProvidedByOperatingActivities": 221295000,
        "investmentsInPropertyPlantAndEquipment": -42185000,
        "acquisitionsNet": -3000,
        "purchasesOfInvestments": 0,
        "salesMaturitiesOfInvestments": 0,
        "otherInvestingActivites": 0,
        "netCashUsedForInvestingActivites": -42188000,
        "debtRepayment": -54469000,
        "commonStockIssued": 32749000,
        "commonStockRepurchased": -2376000,
        "dividendsPaid": 0,
        "otherFinancingActivites": 0,
        "netCashUsedProvidedByFinancingActivities": -24096000,
        "effectOfForexChangesOnCash": 9103000,
        "netChangeInCash": 164114000,
        "cashAtEndOfPeriod": 2983515000,
        "cashAtBeginningOfPeriod": 2819401000,
        "operatingCashFlow": 221295000,
        "capitalExpenditure": -42185000,
        "freeCashFlow": 179110000,
        "link": null,
        "finalLink": null
    },
    {
        "date": "2023-03-31",
        "symbol": "CPAY",
        "reportedCurrency": "USD",
        "cik": "0001175454",
        "fillingDate": "2023-03-31",
        "acceptedDate": "2023-03-30 20:00:00",
        "calendarYear": "2023",
        "period": "Q1",
        "netIncome": 214835000,
        "depreciationAndAmortization": 84232000,
        "deferredIncomeTax": -499000,
        "stockBasedCompensation": 26096000,
        "changeInWorkingCapital": 511471000,
        "accountsReceivables": 372342000,
        "inventory": 0,
        "accountsPayables": 102112000,
        "otherWorkingCapital": 37017000,
        "otherNonCashItems": 41530000,
        "netCashProvidedByOperatingActivities": 877665000,
        "investmentsInPropertyPlantAndEquipment": -36737000,
        "acquisitionsNet": -126691000,
        "purchasesOfInvestments": 0,
        "salesMaturitiesOfInvestments": 0,
        "otherInvestingActivites": 4401000,
        "netCashUsedForInvestingActivites": -159027000,
        "debtRepayment": -241781000,
        "commonStockIssued": 33399000,
        "commonStockRepurchased": -9597000,
        "dividendsPaid": 0,
        "otherFinancingActivites": 264000,
        "netCashUsedProvidedByFinancingActivities": -217715000,
        "effectOfForexChangesOnCash": 29298000,
        "netChangeInCash": 530221000,
        "cashAtEndOfPeriod": 2819401000,
        "cashAtBeginningOfPeriod": 2289180000,
        "operatingCashFlow": 877665000,
        "capitalExpenditure": -36737000,
        "freeCashFlow": 840928000,
        "link": null,
        "finalLink": null
    },
    {
        "date": "2022-12-31",
        "symbol": "CPAY",
        "reportedCurrency": "USD",
        "cik": "0001175454",
        "fillingDate": "2022-12-31",
        "acceptedDate": "2022-12-30 19:00:00",
        "calendarYear": "2022",
        "period": "Q4",
        "netIncome": 225319000,
        "depreciationAndAmortization": 89793000,
        "deferredIncomeTax": -25187000,
        "stockBasedCompensation": 20588000,
        "changeInWorkingCapital": -38305000,
        "accountsReceivables": 351563000,
        "inventory": 0,
        "accountsPayables": -725610000,
        "otherWorkingCapital": 335742000,
        "otherNonCashItems": 43982000,
        "netCashProvidedByOperatingActivities": 316190000,
        "investmentsInPropertyPlantAndEquipment": -43797000,
        "acquisitionsNet": -56800000,
        "purchasesOfInvestments": 0,
        "salesMaturitiesOfInvestments": 0,
        "otherInvestingActivites": 0,
        "netCashUsedForInvestingActivites": -100597000,
        "debtRepayment": -188500000,
        "commonStockIssued": 27295000,
        "commonStockRepurchased": -109556000,
        "dividendsPaid": 0,
        "otherFinancingActivites": -344000,
        "netCashUsedProvidedByFinancingActivities": -271105000,
        "effectOfForexChangesOnCash": 43812000,
        "netChangeInCash": -11700000,
        "cashAtEndOfPeriod": 2289180000,
        "cashAtBeginningOfPeriod": 2300880000,
        "operatingCashFlow": 316190000,
        "capitalExpenditure": -43797000,
        "freeCashFlow": 272393000,
        "link": null,
        "finalLink": null
    },
    {
        "date": "2022-09-30",
        "symbol": "CPAY",
        "reportedCurrency": "USD",
        "cik": "0001175454",
        "fillingDate": "2022-09-30",
        "acceptedDate": "2022-09-29 20:00:00",
        "calendarYear": "2022",
        "period": "Q3",
        "netIncome": 248885000,
        "depreciationAndAmortization": 77213000,
        "deferredIncomeTax": 2877000,
        "stockBasedCompensation": 34180000,
        "changeInWorkingCapital": -5667000,
        "accountsReceivables": 275468000,
        "inventory": 0,
        "accountsPayables": 130683000,
        "otherWorkingCapital": -411818000,
        "otherNonCashItems": 39266000,
        "netCashProvidedByOperatingActivities": 396754000,
        "investmentsInPropertyPlantAndEquipment": -41002000,
        "acquisitionsNet": -126373000,
        "purchasesOfInvestments": 0,
        "salesMaturitiesOfInvestments": 0,
        "otherInvestingActivites": 0,
        "netCashUsedForInvestingActivites": -167375000,
        "debtRepayment": 344500000,
        "commonStockIssued": 3272000,
        "commonStockRepurchased": -500342000,
        "dividendsPaid": 0,
        "otherFinancingActivites": -9945000,
        "netCashUsedProvidedByFinancingActivities": -162515000,
        "effectOfForexChangesOnCash": -122417000,
        "netChangeInCash": -55553000,
        "cashAtEndOfPeriod": 2300880000,
        "cashAtBeginningOfPeriod": 2356433000,
        "operatingCashFlow": 396754000,
        "capitalExpenditure": -41002000,
        "freeCashFlow": 355752000,
        "link": null,
        "finalLink": null
    },
    {
        "date": "2022-06-30",
        "symbol": "CPAY",
        "reportedCurrency": "USD",
        "cik": "0001175454",
        "fillingDate": "2022-06-30",
        "acceptedDate": "2022-06-29 20:00:00",
        "calendarYear": "2022",
        "period": "Q2",
        "netIncome": 262171000,
        "depreciationAndAmortization": 78474000,
        "deferredIncomeTax": -12764000,
        "stockBasedCompensation": 34017000,
        "changeInWorkingCapital": 83993000,
        "accountsReceivables": -406736000,
        "inventory": 0,
        "accountsPayables": 273463000,
        "otherWorkingCapital": 217266000,
        "otherNonCashItems": -291785000,
        "netCashProvidedByOperatingActivities": 154106000,
        "investmentsInPropertyPlantAndEquipment": -35242000,
        "acquisitionsNet": 2120000,
        "purchasesOfInvestments": 0,
        "salesMaturitiesOfInvestments": 0,
        "otherInvestingActivites": 0,
        "netCashUsedForInvestingActivites": -33122000,
        "debtRepayment": 534752000,
        "commonStockIssued": 10027000,
        "commonStockRepurchased": -372566000,
        "dividendsPaid": 0,
        "otherFinancingActivites": 0,
        "netCashUsedProvidedByFinancingActivities": 172213000,
        "effectOfForexChangesOnCash": -26202000,
        "netChangeInCash": 266995000,
        "cashAtEndOfPeriod": 2356433000,
        "cashAtBeginningOfPeriod": 2089438000,
        "operatingCashFlow": 154106000,
        "capitalExpenditure": -35242000,
        "freeCashFlow": 118864000,
        "link": null,
        "finalLink": null
    },
    {
        "date": "2022-03-31",
        "symbol": "CPAY",
        "reportedCurrency": "USD",
        "cik": "0001175454",
        "fillingDate": "2022-03-31",
        "acceptedDate": "2022-03-30 20:00:00",
        "calendarYear": "2022",
        "period": "Q1",
        "netIncome": 217952000,
        "depreciationAndAmortization": 76802000,
        "deferredIncomeTax": 1900000,
        "stockBasedCompensation": 32631000,
        "changeInWorkingCapital": -792517000,
        "accountsReceivables": -818969000,
        "inventory": 0,
        "accountsPayables": 381921000,
        "otherWorkingCapital": -355469000,
        "otherNonCashItems": 350979000,
        "netCashProvidedByOperatingActivities": -112253000,
        "investmentsInPropertyPlantAndEquipment": -31387000,
        "acquisitionsNet": -35864000,
        "purchasesOfInvestments": 0,
        "salesMaturitiesOfInvestments": 0,
        "otherInvestingActivites": 0,
        "netCashUsedForInvestingActivites": -67251000,
        "debtRepayment": 364442000,
        "commonStockIssued": 8810000,
        "commonStockRepurchased": -422736000,
        "dividendsPaid": 0,
        "otherFinancingActivites": -337000,
        "netCashUsedProvidedByFinancingActivities": -49821000,
        "effectOfForexChangesOnCash": 68068000,
        "netChangeInCash": -161257000,
        "cashAtEndOfPeriod": 2089438000,
        "cashAtBeginningOfPeriod": 2250695000,
        "operatingCashFlow": -112253000,
        "capitalExpenditure": -31387000,
        "freeCashFlow": -143640000,
        "link": null,
        "finalLink": null
    },
    {
        "date": "2021-12-31",
        "symbol": "CPAY",
        "reportedCurrency": "USD",
        "cik": "0001175454",
        "fillingDate": "2021-12-31",
        "acceptedDate": "2021-12-30 19:00:00",
        "calendarYear": "2021",
        "period": "Q4",
        "netIncome": 225004000,
        "depreciationAndAmortization": 75012000,
        "deferredIncomeTax": -5220000,
        "stockBasedCompensation": 27986000,
        "changeInWorkingCapital": 245213000,
        "accountsReceivables": 289763000,
        "inventory": 0,
        "accountsPayables": -48737000,
        "otherWorkingCapital": 4187000,
        "otherNonCashItems": 29527000,
        "netCashProvidedByOperatingActivities": 597522000,
        "investmentsInPropertyPlantAndEquipment": -37075000,
        "acquisitionsNet": -57068000,
        "purchasesOfInvestments": 0,
        "salesMaturitiesOfInvestments": 0,
        "otherInvestingActivites": 0,
        "netCashUsedForInvestingActivites": -94143000,
        "debtRepayment": 314938000,
        "commonStockIssued": 622000,
        "commonStockRepurchased": -533445000,
        "dividendsPaid": 0,
        "otherFinancingActivites": -17412000,
        "netCashUsedProvidedByFinancingActivities": -235297000,
        "effectOfForexChangesOnCash": -26324000,
        "netChangeInCash": 241758000,
        "cashAtEndOfPeriod": 2250695000,
        "cashAtBeginningOfPeriod": 2008937000,
        "operatingCashFlow": 597522000,
        "capitalExpenditure": -37075000,
        "freeCashFlow": 560447000,
        "link": null,
        "finalLink": null
    },
    {
        "date": "2021-09-30",
        "symbol": "CPAY",
        "reportedCurrency": "USD",
        "cik": "0001175454",
        "fillingDate": "2021-09-30",
        "acceptedDate": "2021-09-29 20:00:00",
        "calendarYear": "2021",
        "period": "Q3",
        "netIncome": 234007000,
        "depreciationAndAmortization": 74237000,
        "deferredIncomeTax": 1835000,
        "stockBasedCompensation": 16453000,
        "changeInWorkingCapital": -95986000,
        "accountsReceivables": -314326000,
        "inventory": 0,
        "accountsPayables": 135381000,
        "otherWorkingCapital": 82959000,
        "otherNonCashItems": 12553000,
        "netCashProvidedByOperatingActivities": 243099000,
        "investmentsInPropertyPlantAndEquipment": -28690000,
        "acquisitionsNet": -430058000,
        "purchasesOfInvestments": 0,
        "salesMaturitiesOfInvestments": 0,
        "otherInvestingActivites": 0,
        "netCashUsedForInvestingActivites": -458748000,
        "debtRepayment": 538515000,
        "commonStockIssued": 12238000,
        "commonStockRepurchased": -405692000,
        "dividendsPaid": 0,
        "otherFinancingActivites": 75491000,
        "netCashUsedProvidedByFinancingActivities": 220552000,
        "effectOfForexChangesOnCash": -55269000,
        "netChangeInCash": -50366000,
        "cashAtEndOfPeriod": 2008937000,
        "cashAtBeginningOfPeriod": 2059303000,
        "operatingCashFlow": 243099000,
        "capitalExpenditure": -28690000,
        "freeCashFlow": 214409000,
        "link": null,
        "finalLink": null
    },
    {
        "date": "2021-06-30",
        "symbol": "CPAY",
        "reportedCurrency": "USD",
        "cik": "0001175454",
        "fillingDate": "2021-06-30",
        "acceptedDate": "2021-06-29 20:00:00",
        "calendarYear": "2021",
        "period": "Q2",
        "netIncome": 196247000,
        "depreciationAndAmortization": 69218000,
        "deferredIncomeTax": 3719000,
        "stockBasedCompensation": 17885000,
        "changeInWorkingCapital": -22552000,
        "accountsReceivables": -237981000,
        "inventory": 0,
        "accountsPayables": 143353000,
        "otherWorkingCapital": 72076000,
        "otherNonCashItems": 14075000,
        "netCashProvidedByOperatingActivities": 278592000,
        "investmentsInPropertyPlantAndEquipment": -26239000,
        "acquisitionsNet": -71267000,
        "purchasesOfInvestments": 0,
        "salesMaturitiesOfInvestments": 0,
        "otherInvestingActivites": -2290000,
        "netCashUsedForInvestingActivites": -99796000,
        "debtRepayment": 397935000,
        "commonStockIssued": 8576000,
        "commonStockRepurchased": -254544000,
        "dividendsPaid": 0,
        "otherFinancingActivites": 223285000,
        "netCashUsedProvidedByFinancingActivities": 375252000,
        "effectOfForexChangesOnCash": 73733000,
        "netChangeInCash": 627781000,
        "cashAtEndOfPeriod": 2059303000,
        "cashAtBeginningOfPeriod": 1431522000,
        "operatingCashFlow": 278592000,
        "capitalExpenditure": -26239000,
        "freeCashFlow": 252353000,
        "link": null,
        "finalLink": null
    },
    {
        "date": "2021-03-31",
        "symbol": "CPAY",
        "reportedCurrency": "USD",
        "cik": "0001175454",
        "fillingDate": "2021-03-31",
        "acceptedDate": "2021-03-30 20:00:00",
        "calendarYear": "2021",
        "period": "Q1",
        "netIncome": 184239000,
        "depreciationAndAmortization": 65729000,
        "deferredIncomeTax": 4497000,
        "stockBasedCompensation": 17747000,
        "changeInWorkingCapital": -198358000,
        "accountsReceivables": -468593000,
        "inventory": 0,
        "accountsPayables": 206357000,
        "otherWorkingCapital": 63878000,
        "otherNonCashItems": 3996000,
        "netCashProvidedByOperatingActivities": 77850000,
        "investmentsInPropertyPlantAndEquipment": -19526000,
        "acquisitionsNet": -43727000,
        "purchasesOfInvestments": 0,
        "salesMaturitiesOfInvestments": 9000,
        "otherInvestingActivites": 0,
        "netCashUsedForInvestingActivites": -63244000,
        "debtRepayment": 116650000,
        "commonStockIssued": 27345000,
        "commonStockRepurchased": -162041000,
        "dividendsPaid": 0,
        "otherFinancingActivites": 1467000,
        "netCashUsedProvidedByFinancingActivities": -16579000,
        "effectOfForexChangesOnCash": -43124000,
        "netChangeInCash": -45097000,
        "cashAtEndOfPeriod": 1431522000,
        "cashAtBeginningOfPeriod": 1476619000,
        "operatingCashFlow": 77850000,
        "capitalExpenditure": -19526000,
        "freeCashFlow": 58324000,
        "link": null,
        "finalLink": null
    },
    {
        "date": "2020-12-31",
        "symbol": "CPAY",
        "reportedCurrency": "USD",
        "cik": "0001175454",
        "fillingDate": "2020-12-31",
        "acceptedDate": "2020-12-30 19:00:00",
        "calendarYear": "2020",
        "period": "Q4",
        "netIncome": 209851000,
        "depreciationAndAmortization": 64684000,
        "deferredIncomeTax": -9365000,
        "stockBasedCompensation": 8315000,
        "changeInWorkingCapital": -21611000,
        "accountsReceivables": 214450000,
        "inventory": 0,
        "accountsPayables": 0,
        "otherWorkingCapital": -236061000,
        "otherNonCashItems": 6019000,
        "netCashProvidedByOperatingActivities": 257893000,
        "investmentsInPropertyPlantAndEquipment": -23406000,
        "acquisitionsNet": -8230000,
        "purchasesOfInvestments": 0,
        "salesMaturitiesOfInvestments": 0,
        "otherInvestingActivites": 0,
        "netCashUsedForInvestingActivites": -31636000,
        "debtRepayment": -174127000,
        "commonStockIssued": 41017000,
        "commonStockRepurchased": -61501000,
        "dividendsPaid": 0,
        "otherFinancingActivites": -263000,
        "netCashUsedProvidedByFinancingActivities": -194874000,
        "effectOfForexChangesOnCash": 74376000,
        "netChangeInCash": 105759000,
        "cashAtEndOfPeriod": 1476619000,
        "cashAtBeginningOfPeriod": 1370860000,
        "operatingCashFlow": 257893000,
        "capitalExpenditure": -23406000,
        "freeCashFlow": 234487000,
        "link": null,
        "finalLink": null
    },
    {
        "date": "2020-09-30",
        "symbol": "CPAY",
        "reportedCurrency": "USD",
        "cik": "0001175454",
        "fillingDate": "2020-09-30",
        "acceptedDate": "2020-09-29 20:00:00",
        "calendarYear": "2020",
        "period": "Q3",
        "netIncome": 188817000,
        "depreciationAndAmortization": 63479000,
        "deferredIncomeTax": 2983000,
        "stockBasedCompensation": 11905000,
        "changeInWorkingCapital": 128601000,
        "accountsReceivables": -309995000,
        "inventory": 0,
        "accountsPayables": 0,
        "otherWorkingCapital": 438596000,
        "otherNonCashItems": 16743000,
        "netCashProvidedByOperatingActivities": 412528000,
        "investmentsInPropertyPlantAndEquipment": -18149000,
        "acquisitionsNet": -72065000,
        "purchasesOfInvestments": 0,
        "salesMaturitiesOfInvestments": 0,
        "otherInvestingActivites": 52963000,
        "netCashUsedForInvestingActivites": -37251000,
        "debtRepayment": 40326000,
        "commonStockIssued": 2803000,
        "commonStockRepurchased": -231048000,
        "dividendsPaid": 0,
        "otherFinancingActivites": -1575000,
        "netCashUsedProvidedByFinancingActivities": -189494000,
        "effectOfForexChangesOnCash": -6269000,
        "netChangeInCash": 179514000,
        "cashAtEndOfPeriod": 1370860000,
        "cashAtBeginningOfPeriod": 1191346000,
        "operatingCashFlow": 412528000,
        "capitalExpenditure": -18149000,
        "freeCashFlow": 394379000,
        "link": null,
        "finalLink": null
    },
    {
        "date": "2020-06-30",
        "symbol": "CPAY",
        "reportedCurrency": "USD",
        "cik": "0001175454",
        "fillingDate": "2020-06-30",
        "acceptedDate": "2020-06-29 20:00:00",
        "calendarYear": "2020",
        "period": "Q2",
        "netIncome": 158488000,
        "depreciationAndAmortization": 62162000,
        "deferredIncomeTax": -1408000,
        "stockBasedCompensation": 8989000,
        "changeInWorkingCapital": 165057000,
        "accountsReceivables": 203633000,
        "inventory": 0,
        "accountsPayables": 0,
        "otherWorkingCapital": -38576000,
        "otherNonCashItems": -11153000,
        "netCashProvidedByOperatingActivities": 382135000,
        "investmentsInPropertyPlantAndEquipment": -18613000,
        "acquisitionsNet": -25000,
        "purchasesOfInvestments": 0,
        "salesMaturitiesOfInvestments": 0,
        "otherInvestingActivites": 0,
        "netCashUsedForInvestingActivites": -18638000,
        "debtRepayment": -709510000,
        "commonStockIssued": 19703000,
        "commonStockRepurchased": -27124000,
        "dividendsPaid": 0,
        "otherFinancingActivites": -1051000,
        "netCashUsedProvidedByFinancingActivities": -717982000,
        "effectOfForexChangesOnCash": -6405000,
        "netChangeInCash": -360890000,
        "cashAtEndOfPeriod": 1191346000,
        "cashAtBeginningOfPeriod": 1552236000,
        "operatingCashFlow": 382135000,
        "capitalExpenditure": -18613000,
        "freeCashFlow": 363522000,
        "link": null,
        "finalLink": null
    },
    {
        "date": "2020-03-31",
        "symbol": "CPAY",
        "reportedCurrency": "USD",
        "cik": "0001175454",
        "fillingDate": "2020-03-31",
        "acceptedDate": "2020-03-30 20:00:00",
        "calendarYear": "2020",
        "period": "Q1",
        "netIncome": 147060000,
        "depreciationAndAmortization": 64476000,
        "deferredIncomeTax": -7322000,
        "stockBasedCompensation": 14175000,
        "changeInWorkingCapital": 80211000,
        "accountsReceivables": 156052000,
        "inventory": 0,
        "accountsPayables": 0,
        "otherWorkingCapital": -75841000,
        "otherNonCashItems": 121433000,
        "netCashProvidedByOperatingActivities": 420033000,
        "investmentsInPropertyPlantAndEquipment": -18257000,
        "acquisitionsNet": -467000,
        "purchasesOfInvestments": 0,
        "salesMaturitiesOfInvestments": 0,
        "otherInvestingActivites": 0,
        "netCashUsedForInvestingActivites": -18724000,
        "debtRepayment": 142604000,
        "commonStockIssued": 73274000,
        "commonStockRepurchased": -530237000,
        "dividendsPaid": 0,
        "otherFinancingActivites": -92000,
        "netCashUsedProvidedByFinancingActivities": -314451000,
        "effectOfForexChangesOnCash": -209859000,
        "netChangeInCash": -123001000,
        "cashAtEndOfPeriod": 1552236000,
        "cashAtBeginningOfPeriod": 1675237000,
        "operatingCashFlow": 420033000,
        "capitalExpenditure": -18257000,
        "freeCashFlow": 401776000,
        "link": null,
        "finalLink": null
    },
    {
        "date": "2019-12-31",
        "symbol": "CPAY",
        "reportedCurrency": "USD",
        "cik": "0001175454",
        "fillingDate": "2019-12-31",
        "acceptedDate": "2019-12-30 19:00:00",
        "calendarYear": "2019",
        "period": "Q4",
        "netIncome": 235510000,
        "depreciationAndAmortization": 68510000,
        "deferredIncomeTax": 26741000,
        "stockBasedCompensation": 14833000,
        "changeInWorkingCapital": 14293000,
        "accountsReceivables": 276350000,
        "inventory": 0,
        "accountsPayables": 0,
        "otherWorkingCapital": -262057000,
        "otherNonCashItems": 11049000,
        "netCashProvidedByOperatingActivities": 370936000,
        "investmentsInPropertyPlantAndEquipment": -26489000,
        "acquisitionsNet": -113417000,
        "purchasesOfInvestments": 0,
        "salesMaturitiesOfInvestments": 0,
        "otherInvestingActivites": -255000,
        "netCashUsedForInvestingActivites": -140161000,
        "debtRepayment": 534754000,
        "commonStockIssued": 51298000,
        "commonStockRepurchased": -635547000,
        "dividendsPaid": 0,
        "otherFinancingActivites": -206000,
        "netCashUsedProvidedByFinancingActivities": -49701000,
        "effectOfForexChangesOnCash": 28286000,
        "netChangeInCash": 209360000,
        "cashAtEndOfPeriod": 1675237000,
        "cashAtBeginningOfPeriod": 1465877000,
        "operatingCashFlow": 370936000,
        "capitalExpenditure": -26489000,
        "freeCashFlow": 344447000,
        "link": null,
        "finalLink": null
    },
    {
        "date": "2019-09-30",
        "symbol": "CPAY",
        "reportedCurrency": "USD",
        "cik": "0001175454",
        "fillingDate": "2019-09-30",
        "acceptedDate": "2019-09-29 20:00:00",
        "calendarYear": "2019",
        "period": "Q3",
        "netIncome": 225805000,
        "depreciationAndAmortization": 67347000,
        "deferredIncomeTax": 76025000,
        "stockBasedCompensation": 15273000,
        "changeInWorkingCapital": -159043000,
        "accountsReceivables": -53572000,
        "inventory": 0,
        "accountsPayables": 0,
        "otherWorkingCapital": -105471000,
        "otherNonCashItems": 15707000,
        "netCashProvidedByOperatingActivities": 241114000,
        "investmentsInPropertyPlantAndEquipment": -16706000,
        "acquisitionsNet": -83934000,
        "purchasesOfInvestments": 0,
        "salesMaturitiesOfInvestments": 0,
        "otherInvestingActivites": 0,
        "netCashUsedForInvestingActivites": -100640000,
        "debtRepayment": -112130000,
        "commonStockIssued": 60677000,
        "commonStockRepurchased": -55338000,
        "dividendsPaid": 0,
        "otherFinancingActivites": -2133000,
        "netCashUsedProvidedByFinancingActivities": -108924000,
        "effectOfForexChangesOnCash": -54299000,
        "netChangeInCash": -22749000,
        "cashAtEndOfPeriod": 1465877000,
        "cashAtBeginningOfPeriod": 1488626000,
        "operatingCashFlow": 241114000,
        "capitalExpenditure": -16706000,
        "freeCashFlow": 224408000,
        "link": null,
        "finalLink": null
    },
    {
        "date": "2019-06-30",
        "symbol": "CPAY",
        "reportedCurrency": "USD",
        "cik": "0001175454",
        "fillingDate": "2019-06-30",
        "acceptedDate": "2019-06-29 20:00:00",
        "calendarYear": "2019",
        "period": "Q2",
        "netIncome": 261651000,
        "depreciationAndAmortization": 70908000,
        "deferredIncomeTax": -62187000,
        "stockBasedCompensation": 18306000,
        "changeInWorkingCapital": -55347000,
        "accountsReceivables": -116411000,
        "inventory": 0,
        "accountsPayables": 0,
        "otherWorkingCapital": 61064000,
        "otherNonCashItems": 19196000,
        "netCashProvidedByOperatingActivities": 252527000,
        "investmentsInPropertyPlantAndEquipment": -17469000,
        "acquisitionsNet": -250926000,
        "purchasesOfInvestments": 0,
        "salesMaturitiesOfInvestments": 0,
        "otherInvestingActivites": 0,
        "netCashUsedForInvestingActivites": -268395000,
        "debtRepayment": 95049000,
        "commonStockIssued": 27155000,
        "commonStockRepurchased": -702000,
        "dividendsPaid": 0,
        "otherFinancingActivites": -130000,
        "netCashUsedProvidedByFinancingActivities": 121372000,
        "effectOfForexChangesOnCash": 10551000,
        "netChangeInCash": 116055000,
        "cashAtEndOfPeriod": 1488626000,
        "cashAtBeginningOfPeriod": 1372571000,
        "operatingCashFlow": 252527000,
        "capitalExpenditure": -17469000,
        "freeCashFlow": 235058000,
        "link": null,
        "finalLink": null
    },
    {
        "date": "2019-03-31",
        "symbol": "CPAY",
        "reportedCurrency": "USD",
        "cik": "0001175454",
        "fillingDate": "2019-03-31",
        "acceptedDate": "2019-03-30 20:00:00",
        "calendarYear": "2019",
        "period": "Q1",
        "netIncome": 172107000,
        "depreciationAndAmortization": 67445000,
        "deferredIncomeTax": -2696000,
        "stockBasedCompensation": 12541000,
        "changeInWorkingCapital": 10642000,
        "accountsReceivables": -302395000,
        "inventory": 0,
        "accountsPayables": 0,
        "otherWorkingCapital": 313037000,
        "otherNonCashItems": 37455000,
        "netCashProvidedByOperatingActivities": 297494000,
        "investmentsInPropertyPlantAndEquipment": -14506000,
        "acquisitionsNet": 0,
        "purchasesOfInvestments": 0,
        "salesMaturitiesOfInvestments": 0,
        "otherInvestingActivites": 0,
        "netCashUsedForInvestingActivites": -14506000,
        "debtRepayment": -299044000,
        "commonStockIssued": 29795000,
        "commonStockRepurchased": -3322000,
        "dividendsPaid": 0,
        "otherFinancingActivites": -347000,
        "netCashUsedProvidedByFinancingActivities": -272918000,
        "effectOfForexChangesOnCash": -2392000,
        "netChangeInCash": 7678000,
        "cashAtEndOfPeriod": 1372571000,
        "cashAtBeginningOfPeriod": 1364893000,
        "operatingCashFlow": 297494000,
        "capitalExpenditure": -14506000,
        "freeCashFlow": 282988000,
        "link": null,
        "finalLink": null
    },
    {
        "date": "2018-12-31",
        "symbol": "CPAY",
        "reportedCurrency": "USD",
        "cik": "0001175454",
        "fillingDate": "2018-12-31",
        "acceptedDate": "2018-12-30 19:00:00",
        "calendarYear": "2018",
        "period": "Q4",
        "netIncome": 302000000,
        "depreciationAndAmortization": 66090000,
        "deferredIncomeTax": 3584000,
        "stockBasedCompensation": 15732000,
        "changeInWorkingCapital": 79196000,
        "accountsReceivables": 481835000,
        "inventory": 0,
        "accountsPayables": 0,
        "otherWorkingCapital": -402639000,
        "otherNonCashItems": -118600000,
        "netCashProvidedByOperatingActivities": 348002000,
        "investmentsInPropertyPlantAndEquipment": -25075000,
        "acquisitionsNet": -17044000,
        "purchasesOfInvestments": 0,
        "salesMaturitiesOfInvestments": 0,
        "otherInvestingActivites": 87152000,
        "netCashUsedForInvestingActivites": 45033000,
        "debtRepayment": 352848000,
        "commonStockIssued": 7358000,
        "commonStockRepurchased": -578045000,
        "dividendsPaid": 0,
        "otherFinancingActivites": -3644000,
        "netCashUsedProvidedByFinancingActivities": -221483000,
        "effectOfForexChangesOnCash": 4791000,
        "netChangeInCash": 176343000,
        "cashAtEndOfPeriod": 1364893000,
        "cashAtBeginningOfPeriod": 1188550000,
        "operatingCashFlow": 348002000,
        "capitalExpenditure": -25075000,
        "freeCashFlow": 322927000,
        "link": null,
        "finalLink": null
    },
    {
        "date": "2018-09-30",
        "symbol": "CPAY",
        "reportedCurrency": "USD",
        "cik": "0001175454",
        "fillingDate": "2018-09-30",
        "acceptedDate": "2018-09-29 20:00:00",
        "calendarYear": "2018",
        "period": "Q3",
        "netIncome": 157694000,
        "depreciationAndAmortization": 67266000,
        "deferredIncomeTax": 139000,
        "stockBasedCompensation": 20702000,
        "changeInWorkingCapital": 8997000,
        "accountsReceivables": -121332000,
        "inventory": 0,
        "accountsPayables": 0,
        "otherWorkingCapital": 130329000,
        "otherNonCashItems": 25493000,
        "netCashProvidedByOperatingActivities": 280291000,
        "investmentsInPropertyPlantAndEquipment": -21698000,
        "acquisitionsNet": 12000,
        "purchasesOfInvestments": 0,
        "salesMaturitiesOfInvestments": 0,
        "otherInvestingActivites": 0,
        "netCashUsedForInvestingActivites": -21686000,
        "debtRepayment": -270149000,
        "commonStockIssued": 18824000,
        "commonStockRepurchased": 0,
        "dividendsPaid": 0,
        "otherFinancingActivites": -247000,
        "netCashUsedProvidedByFinancingActivities": -251572000,
        "effectOfForexChangesOnCash": -3921000,
        "netChangeInCash": 3112000,
        "cashAtEndOfPeriod": 1188550000,
        "cashAtBeginningOfPeriod": 1185438000,
        "operatingCashFlow": 280291000,
        "capitalExpenditure": -21698000,
        "freeCashFlow": 258593000,
        "link": null,
        "finalLink": null
    },
    {
        "date": "2018-06-30",
        "symbol": "CPAY",
        "reportedCurrency": "USD",
        "cik": "0001175454",
        "fillingDate": "2018-06-30",
        "acceptedDate": "2018-06-29 20:00:00",
        "calendarYear": "2018",
        "period": "Q2",
        "netIncome": 176852000,
        "depreciationAndAmortization": 68610000,
        "deferredIncomeTax": -1644000,
        "stockBasedCompensation": 19102000,
        "changeInWorkingCapital": -204323000,
        "accountsReceivables": -231375000,
        "inventory": 0,
        "accountsPayables": 0,
        "otherWorkingCapital": 27052000,
        "otherNonCashItems": 15790000,
        "netCashProvidedByOperatingActivities": 74387000,
        "investmentsInPropertyPlantAndEquipment": -19400000,
        "acquisitionsNet": 64000,
        "purchasesOfInvestments": 0,
        "salesMaturitiesOfInvestments": 0,
        "otherInvestingActivites": -7550000,
        "netCashUsedForInvestingActivites": -26886000,
        "debtRepayment": 277126000,
        "commonStockIssued": 9523000,
        "commonStockRepurchased": -292359000,
        "dividendsPaid": 0,
        "otherFinancingActivites": -57000,
        "netCashUsedProvidedByFinancingActivities": -5767000,
        "effectOfForexChangesOnCash": -78797000,
        "netChangeInCash": -37063000,
        "cashAtEndOfPeriod": 1185438000,
        "cashAtBeginningOfPeriod": 1222501000,
        "operatingCashFlow": 74387000,
        "capitalExpenditure": -19400000,
        "freeCashFlow": 54987000,
        "link": null,
        "finalLink": null
    },
    {
        "date": "2018-03-31",
        "symbol": "CPAY",
        "reportedCurrency": "USD",
        "cik": "0001175454",
        "fillingDate": "2018-03-31",
        "acceptedDate": "2018-03-30 20:00:00",
        "calendarYear": "2018",
        "period": "Q1",
        "netIncome": 174937000,
        "depreciationAndAmortization": 71502000,
        "deferredIncomeTax": -4829000,
        "stockBasedCompensation": 14403000,
        "changeInWorkingCapital": -68590000,
        "accountsReceivables": -288152000,
        "inventory": 0,
        "accountsPayables": 0,
        "otherWorkingCapital": 219562000,
        "otherNonCashItems": 13279000,
        "netCashProvidedByOperatingActivities": 200702000,
        "investmentsInPropertyPlantAndEquipment": -15214000,
        "acquisitionsNet": -3875000,
        "purchasesOfInvestments": 0,
        "salesMaturitiesOfInvestments": 0,
        "otherInvestingActivites": -3642000,
        "netCashUsedForInvestingActivites": -22731000,
        "debtRepayment": -30584000,
        "commonStockIssued": 19975000,
        "commonStockRepurchased": -88292000,
        "dividendsPaid": 0,
        "otherFinancingActivites": -92000,
        "netCashUsedProvidedByFinancingActivities": -98993000,
        "effectOfForexChangesOnCash": 12653000,
        "netChangeInCash": 91631000,
        "cashAtEndOfPeriod": 1222501000,
        "cashAtBeginningOfPeriod": 1130870000,
        "operatingCashFlow": 200702000,
        "capitalExpenditure": -15214000,
        "freeCashFlow": 185488000,
        "link": null,
        "finalLink": null
    },
    {
        "date": "2017-12-31",
        "symbol": "CPAY",
        "reportedCurrency": "USD",
        "cik": "0001175454",
        "fillingDate": "2017-12-31",
        "acceptedDate": "2017-12-30 19:00:00",
        "calendarYear": "2017",
        "period": "Q4",
        "netIncome": 282697000,
        "depreciationAndAmortization": 64455000,
        "deferredIncomeTax": -209620000,
        "stockBasedCompensation": 24400000,
        "changeInWorkingCapital": 81822000,
        "accountsReceivables": 9008000,
        "inventory": 0,
        "accountsPayables": 0,
        "otherWorkingCapital": 72814000,
        "otherNonCashItems": 12479000,
        "netCashProvidedByOperatingActivities": 256233000,
        "investmentsInPropertyPlantAndEquipment": -20634000,
        "acquisitionsNet": -102959000,
        "purchasesOfInvestments": 0,
        "salesMaturitiesOfInvestments": 0,
        "otherInvestingActivites": -32626000,
        "netCashUsedForInvestingActivites": -156219000,
        "debtRepayment": -20900000,
        "commonStockIssued": 24498000,
        "commonStockRepurchased": -1000,
        "dividendsPaid": 0,
        "otherFinancingActivites": -1758000,
        "netCashUsedProvidedByFinancingActivities": 1839000,
        "effectOfForexChangesOnCash": 18516000,
        "netChangeInCash": 78839000,
        "cashAtEndOfPeriod": 1130870000,
        "cashAtBeginningOfPeriod": 1018271000,
        "operatingCashFlow": 248463000,
        "capitalExpenditure": -20634000,
        "freeCashFlow": 227829000,
        "link": null,
        "finalLink": null
    },
    {
        "date": "2017-09-30",
        "symbol": "CPAY",
        "reportedCurrency": "USD",
        "cik": "0001175454",
        "fillingDate": "2017-09-30",
        "acceptedDate": "2017-09-29 20:00:00",
        "calendarYear": "2017",
        "period": "Q3",
        "netIncome": 202823000,
        "depreciationAndAmortization": 67506000,
        "deferredIncomeTax": -5432000,
        "stockBasedCompensation": 24654000,
        "changeInWorkingCapital": 46710000,
        "accountsReceivables": -59815000,
        "inventory": 0,
        "accountsPayables": 0,
        "otherWorkingCapital": 106525000,
        "otherNonCashItems": -112409000,
        "netCashProvidedByOperatingActivities": 223852000,
        "investmentsInPropertyPlantAndEquipment": -16859000,
        "acquisitionsNet": -598718000,
        "purchasesOfInvestments": 0,
        "salesMaturitiesOfInvestments": 0,
        "otherInvestingActivites": 316501000,
        "netCashUsedForInvestingActivites": -299076000,
        "debtRepayment": 675373000,
        "commonStockIssued": 3760000,
        "commonStockRepurchased": -349999000,
        "dividendsPaid": 0,
        "otherFinancingActivites": -11230000,
        "netCashUsedProvidedByFinancingActivities": 317904000,
        "effectOfForexChangesOnCash": 9974000,
        "netChangeInCash": 252654000,
        "cashAtEndOfPeriod": 1018271000,
        "cashAtBeginningOfPeriod": 765617000,
        "operatingCashFlow": 223852000,
        "capitalExpenditure": -16859000,
        "freeCashFlow": 206993000,
        "link": null,
        "finalLink": null
    },
    {
        "date": "2017-06-30",
        "symbol": "CPAY",
        "reportedCurrency": "USD",
        "cik": "0001175454",
        "fillingDate": "2017-06-30",
        "acceptedDate": "2017-06-29 20:00:00",
        "calendarYear": "2017",
        "period": "Q2",
        "netIncome": 130987000,
        "depreciationAndAmortization": 63166000,
        "deferredIncomeTax": -29207000,
        "stockBasedCompensation": 21150000,
        "changeInWorkingCapital": -72295000,
        "accountsReceivables": -143632000,
        "inventory": 0,
        "accountsPayables": 0,
        "otherWorkingCapital": 71337000,
        "otherNonCashItems": 20444000,
        "netCashProvidedByOperatingActivities": 134245000,
        "investmentsInPropertyPlantAndEquipment": -17804000,
        "acquisitionsNet": -3580000,
        "purchasesOfInvestments": 0,
        "salesMaturitiesOfInvestments": 0,
        "otherInvestingActivites": 0,
        "netCashUsedForInvestingActivites": -21384000,
        "debtRepayment": -35708000,
        "commonStockIssued": 1202000,
        "commonStockRepurchased": -52393000,
        "dividendsPaid": 0,
        "otherFinancingActivites": 0,
        "netCashUsedProvidedByFinancingActivities": -86899000,
        "effectOfForexChangesOnCash": 4662000,
        "netChangeInCash": 30624000,
        "cashAtEndOfPeriod": 765617000,
        "cashAtBeginningOfPeriod": 734993000,
        "operatingCashFlow": 134245000,
        "capitalExpenditure": -17804000,
        "freeCashFlow": 116441000,
        "link": null,
        "finalLink": null
    },
    {
        "date": "2017-03-31",
        "symbol": "CPAY",
        "reportedCurrency": "USD",
        "cik": "0001175454",
        "fillingDate": "2017-03-31",
        "acceptedDate": "2017-03-30 20:00:00",
        "calendarYear": "2017",
        "period": "Q1",
        "netIncome": 123693000,
        "depreciationAndAmortization": 63321000,
        "deferredIncomeTax": -3453000,
        "stockBasedCompensation": 23093000,
        "changeInWorkingCapital": -151979000,
        "accountsReceivables": -236564000,
        "inventory": 0,
        "accountsPayables": 0,
        "otherWorkingCapital": 84585000,
        "otherNonCashItems": 18823000,
        "netCashProvidedByOperatingActivities": 73498000,
        "investmentsInPropertyPlantAndEquipment": -14796000,
        "acquisitionsNet": 0,
        "purchasesOfInvestments": 0,
        "salesMaturitiesOfInvestments": 0,
        "otherInvestingActivites": -6327000,
        "netCashUsedForInvestingActivites": -21123000,
        "debtRepayment": 3327000,
        "commonStockIssued": 15230000,
        "commonStockRepurchased": 0,
        "dividendsPaid": 0,
        "otherFinancingActivites": 537000,
        "netCashUsedProvidedByFinancingActivities": 19094000,
        "effectOfForexChangesOnCash": 19754000,
        "netChangeInCash": 91223000,
        "cashAtEndOfPeriod": 734993000,
        "cashAtBeginningOfPeriod": 475018000,
        "operatingCashFlow": 73498000,
        "capitalExpenditure": -14796000,
        "freeCashFlow": 58702000,
        "link": null,
        "finalLink": null
    },
    {
        "date": "2016-12-31",
        "symbol": "CPAY",
        "reportedCurrency": "USD",
        "cik": "0001175454",
        "fillingDate": "2016-12-31",
        "acceptedDate": "2016-12-30 19:00:00",
        "calendarYear": "2016",
        "period": "Q4",
        "netIncome": 95424000,
        "depreciationAndAmortization": 59930000,
        "deferredIncomeTax": -5115000,
        "stockBasedCompensation": 13921000,
        "changeInWorkingCapital": 83998000,
        "accountsReceivables": 188459000,
        "inventory": 0,
        "accountsPayables": 0,
        "otherWorkingCapital": -104461000,
        "otherNonCashItems": 53468000,
        "netCashProvidedByOperatingActivities": 301626000,
        "investmentsInPropertyPlantAndEquipment": -17134000,
        "acquisitionsNet": -906000,
        "purchasesOfInvestments": 0,
        "salesMaturitiesOfInvestments": 0,
        "otherInvestingActivites": 0,
        "netCashUsedForInvestingActivites": -18040000,
        "debtRepayment": -72866000,
        "commonStockIssued": 2611000,
        "commonStockRepurchased": -152186000,
        "dividendsPaid": 0,
        "otherFinancingActivites": -3000,
        "netCashUsedProvidedByFinancingActivities": -222444000,
        "effectOfForexChangesOnCash": 8441000,
        "netChangeInCash": 69583000,
        "cashAtEndOfPeriod": 475018000,
        "cashAtBeginningOfPeriod": 405435000,
        "operatingCashFlow": 301626000,
        "capitalExpenditure": -17134000,
        "freeCashFlow": 284492000,
        "link": null,
        "finalLink": null
    },
    {
        "date": "2016-09-30",
        "symbol": "CPAY",
        "reportedCurrency": "USD",
        "cik": "0001175454",
        "fillingDate": "2016-09-30",
        "acceptedDate": "2016-09-29 20:00:00",
        "calendarYear": "2016",
        "period": "Q3",
        "netIncome": 129618000,
        "depreciationAndAmortization": 55736000,
        "deferredIncomeTax": -14318000,
        "stockBasedCompensation": 17405000,
        "changeInWorkingCapital": -12745000,
        "accountsReceivables": -134710000,
        "inventory": 0,
        "accountsPayables": 0,
        "otherWorkingCapital": 121965000,
        "otherNonCashItems": 16548000,
        "netCashProvidedByOperatingActivities": 192244000,
        "investmentsInPropertyPlantAndEquipment": -17120000,
        "acquisitionsNet": -1325780000,
        "purchasesOfInvestments": 0,
        "salesMaturitiesOfInvestments": 0,
        "otherInvestingActivites": 9279000,
        "netCashUsedForInvestingActivites": -1333621000,
        "debtRepayment": 1098980000,
        "commonStockIssued": 10656000,
        "commonStockRepurchased": -9455000,
        "dividendsPaid": 0,
        "otherFinancingActivites": -2279000,
        "netCashUsedProvidedByFinancingActivities": 1097902000,
        "effectOfForexChangesOnCash": -44175000,
        "netChangeInCash": -87650000,
        "cashAtEndOfPeriod": 405435000,
        "cashAtBeginningOfPeriod": 493085000,
        "operatingCashFlow": 192244000,
        "capitalExpenditure": -17120000,
        "freeCashFlow": 175124000,
        "link": null,
        "finalLink": null
    },
    {
        "date": "2016-06-30",
        "symbol": "CPAY",
        "reportedCurrency": "USD",
        "cik": "0001175454",
        "fillingDate": "2016-06-30",
        "acceptedDate": "2016-06-29 20:00:00",
        "calendarYear": "2016",
        "period": "Q2",
        "netIncome": 116253000,
        "depreciationAndAmortization": 47087000,
        "deferredIncomeTax": -7120000,
        "stockBasedCompensation": 17434000,
        "changeInWorkingCapital": -86891000,
        "accountsReceivables": -209784000,
        "inventory": 0,
        "accountsPayables": 0,
        "otherWorkingCapital": 122893000,
        "otherNonCashItems": 2656000,
        "netCashProvidedByOperatingActivities": 89419000,
        "investmentsInPropertyPlantAndEquipment": -13018000,
        "acquisitionsNet": -1207000,
        "purchasesOfInvestments": 0,
        "salesMaturitiesOfInvestments": 0,
        "otherInvestingActivites": -2954000,
        "netCashUsedForInvestingActivites": -17179000,
        "debtRepayment": 56125000,
        "commonStockIssued": 0,
        "commonStockRepurchased": -26037000,
        "dividendsPaid": 0,
        "otherFinancingActivites": -647000,
        "netCashUsedProvidedByFinancingActivities": 37018000,
        "effectOfForexChangesOnCash": -15491000,
        "netChangeInCash": 93767000,
        "cashAtEndOfPeriod": 493085000,
        "cashAtBeginningOfPeriod": 399318000,
        "operatingCashFlow": 89419000,
        "capitalExpenditure": -13018000,
        "freeCashFlow": 76401000,
        "link": null,
        "finalLink": null
    },
    {
        "date": "2016-03-31",
        "symbol": "CPAY",
        "reportedCurrency": "USD",
        "cik": "0001175454",
        "fillingDate": "2016-03-31",
        "acceptedDate": "2016-03-30 20:00:00",
        "calendarYear": "2016",
        "period": "Q1",
        "netIncome": 111090000,
        "depreciationAndAmortization": 35338000,
        "deferredIncomeTax": -2128000,
        "stockBasedCompensation": 15186000,
        "changeInWorkingCapital": -48489000,
        "accountsReceivables": -182761000,
        "inventory": 0,
        "accountsPayables": 0,
        "otherWorkingCapital": 134272000,
        "otherNonCashItems": 11626000,
        "netCashProvidedByOperatingActivities": 122623000,
        "investmentsInPropertyPlantAndEquipment": -11739000,
        "acquisitionsNet": -4092000,
        "purchasesOfInvestments": 0,
        "salesMaturitiesOfInvestments": 0,
        "otherInvestingActivites": -4914000,
        "netCashUsedForInvestingActivites": -20745000,
        "debtRepayment": -158875000,
        "commonStockIssued": 387000,
        "commonStockRepurchased": 0,
        "dividendsPaid": 0,
        "otherFinancingActivites": -19000,
        "netCashUsedProvidedByFinancingActivities": -158507000,
        "effectOfForexChangesOnCash": 8795000,
        "netChangeInCash": -47834000,
        "cashAtEndOfPeriod": 399318000,
        "cashAtBeginningOfPeriod": 447152000,
        "operatingCashFlow": 122623000,
        "capitalExpenditure": -11739000,
        "freeCashFlow": 110884000,
        "link": null,
        "finalLink": null
    },
    {
        "date": "2015-12-31",
        "symbol": "CPAY",
        "reportedCurrency": "USD",
        "cik": "0001175454",
        "fillingDate": "2015-12-31",
        "acceptedDate": "2015-12-30 19:00:00",
        "calendarYear": "2015",
        "period": "Q4",
        "netIncome": 52830000,
        "depreciationAndAmortization": 47206000,
        "deferredIncomeTax": 58266000,
        "stockBasedCompensation": 45735000,
        "changeInWorkingCapital": -22816000,
        "accountsReceivables": 111327000,
        "inventory": 0,
        "accountsPayables": 0,
        "otherWorkingCapital": -134143000,
        "otherNonCashItems": 48911000,
        "netCashProvidedByOperatingActivities": 230132000,
        "investmentsInPropertyPlantAndEquipment": -12349000,
        "acquisitionsNet": -39830000,
        "purchasesOfInvestments": 0,
        "salesMaturitiesOfInvestments": 0,
        "otherInvestingActivites": -688000,
        "netCashUsedForInvestingActivites": -52867000,
        "debtRepayment": -151820000,
        "commonStockIssued": 5949000,
        "commonStockRepurchased": 0,
        "dividendsPaid": 0,
        "otherFinancingActivites": 70000,
        "netCashUsedProvidedByFinancingActivities": -145801000,
        "effectOfForexChangesOnCash": -6702000,
        "netChangeInCash": 24762000,
        "cashAtEndOfPeriod": 447152000,
        "cashAtBeginningOfPeriod": 422390000,
        "operatingCashFlow": 230132000,
        "capitalExpenditure": -12349000,
        "freeCashFlow": 217783000,
        "link": null,
        "finalLink": null
    },
    {
        "date": "2015-09-30",
        "symbol": "CPAY",
        "reportedCurrency": "USD",
        "cik": "0001175454",
        "fillingDate": "2015-09-30",
        "acceptedDate": "2015-09-29 20:00:00",
        "calendarYear": "2015",
        "period": "Q3",
        "netIncome": 116770000,
        "depreciationAndAmortization": 47714000,
        "deferredIncomeTax": 13254000,
        "stockBasedCompensation": 13887000,
        "changeInWorkingCapital": 136972000,
        "accountsReceivables": 162218000,
        "inventory": 0,
        "accountsPayables": 0,
        "otherWorkingCapital": -25246000,
        "otherNonCashItems": -2557000,
        "netCashProvidedByOperatingActivities": 326040000,
        "investmentsInPropertyPlantAndEquipment": -13292000,
        "acquisitionsNet": -1285000,
        "purchasesOfInvestments": 0,
        "salesMaturitiesOfInvestments": 0,
        "otherInvestingActivites": -7782000,
        "netCashUsedForInvestingActivites": -22359000,
        "debtRepayment": -269917000,
        "commonStockIssued": 6872000,
        "commonStockRepurchased": 0,
        "dividendsPaid": 0,
        "otherFinancingActivites": 14117000,
        "netCashUsedProvidedByFinancingActivities": -248928000,
        "effectOfForexChangesOnCash": -16538000,
        "netChangeInCash": 38215000,
        "cashAtEndOfPeriod": 422390000,
        "cashAtBeginningOfPeriod": 384175000,
        "operatingCashFlow": 326040000,
        "capitalExpenditure": -13292000,
        "freeCashFlow": 312748000,
        "link": null,
        "finalLink": null
    },
    {
        "date": "2015-06-30",
        "symbol": "CPAY",
        "reportedCurrency": "USD",
        "cik": "0001175454",
        "fillingDate": "2015-06-30",
        "acceptedDate": "2015-06-29 20:00:00",
        "calendarYear": "2015",
        "period": "Q2",
        "netIncome": 98678000,
        "depreciationAndAmortization": 48013000,
        "deferredIncomeTax": -22156000,
        "stockBasedCompensation": 13549000,
        "changeInWorkingCapital": -16089000,
        "accountsReceivables": -119143000,
        "inventory": 0,
        "accountsPayables": 0,
        "otherWorkingCapital": 103054000,
        "otherNonCashItems": 9014000,
        "netCashProvidedByOperatingActivities": 131009000,
        "investmentsInPropertyPlantAndEquipment": -8129000,
        "acquisitionsNet": -7103000,
        "purchasesOfInvestments": 0,
        "salesMaturitiesOfInvestments": 0,
        "otherInvestingActivites": 0,
        "netCashUsedForInvestingActivites": -15232000,
        "debtRepayment": -118381000,
        "commonStockIssued": 4534000,
        "commonStockRepurchased": 0,
        "dividendsPaid": 0,
        "otherFinancingActivites": 3152000,
        "netCashUsedProvidedByFinancingActivities": -110695000,
        "effectOfForexChangesOnCash": -300000,
        "netChangeInCash": 4782000,
        "cashAtEndOfPeriod": 384175000,
        "cashAtBeginningOfPeriod": 379393000,
        "operatingCashFlow": 131009000,
        "capitalExpenditure": -8129000,
        "freeCashFlow": 122880000,
        "link": null,
        "finalLink": null
    },
    {
        "date": "2015-03-31",
        "symbol": "CPAY",
        "reportedCurrency": "USD",
        "cik": "0001175454",
        "fillingDate": "2015-03-31",
        "acceptedDate": "2015-03-30 20:00:00",
        "calendarYear": "2015",
        "period": "Q1",
        "netIncome": 94153000,
        "depreciationAndAmortization": 47269000,
        "deferredIncomeTax": -18738000,
        "stockBasedCompensation": 16951000,
        "changeInWorkingCapital": -78791000,
        "accountsReceivables": -114385000,
        "inventory": 0,
        "accountsPayables": 0,
        "otherWorkingCapital": 35594000,
        "otherNonCashItems": 6559000,
        "netCashProvidedByOperatingActivities": 67403000,
        "investmentsInPropertyPlantAndEquipment": -8105000,
        "acquisitionsNet": -851000,
        "purchasesOfInvestments": 0,
        "salesMaturitiesOfInvestments": 0,
        "otherInvestingActivites": 0,
        "netCashUsedForInvestingActivites": -8956000,
        "debtRepayment": -111746000,
        "commonStockIssued": 2571000,
        "commonStockRepurchased": 0,
        "dividendsPaid": 0,
        "otherFinancingActivites": -33466000,
        "netCashUsedProvidedByFinancingActivities": -142641000,
        "effectOfForexChangesOnCash": -13482000,
        "netChangeInCash": -97676000,
        "cashAtEndOfPeriod": 379393000,
        "cashAtBeginningOfPeriod": 477069000,
        "operatingCashFlow": 67403000,
        "capitalExpenditure": -8105000,
        "freeCashFlow": 59298000,
        "link": null,
        "finalLink": null
    },
    {
        "date": "2014-12-31",
        "symbol": "CPAY",
        "reportedCurrency": "USD",
        "cik": "0001175454",
        "fillingDate": "2014-12-31",
        "acceptedDate": "2014-12-30 19:00:00",
        "calendarYear": "2014",
        "period": "Q4",
        "netIncome": 109540000,
        "depreciationAndAmortization": 36729000,
        "deferredIncomeTax": -40436000,
        "stockBasedCompensation": 11357000,
        "changeInWorkingCapital": 175717000,
        "accountsReceivables": 384407000,
        "inventory": 0,
        "accountsPayables": 0,
        "otherWorkingCapital": -208690000,
        "otherNonCashItems": -2065000,
        "netCashProvidedByOperatingActivities": 290842000,
        "investmentsInPropertyPlantAndEquipment": -8791000,
        "acquisitionsNet": -2305098000,
        "purchasesOfInvestments": 0,
        "salesMaturitiesOfInvestments": 0,
        "otherInvestingActivites": 0,
        "netCashUsedForInvestingActivites": -2313889000,
        "debtRepayment": 2250866000,
        "commonStockIssued": 7719000,
        "commonStockRepurchased": 0,
        "dividendsPaid": 0,
        "otherFinancingActivites": -40127000,
        "netCashUsedProvidedByFinancingActivities": 2218458000,
        "effectOfForexChangesOnCash": -22451000,
        "netChangeInCash": 172960000,
        "cashAtEndOfPeriod": 477069000,
        "cashAtBeginningOfPeriod": 304109000,
        "operatingCashFlow": 290842000,
        "capitalExpenditure": -8791000,
        "freeCashFlow": 282051000,
        "link": null,
        "finalLink": null
    },
    {
        "date": "2014-09-30",
        "symbol": "CPAY",
        "reportedCurrency": "USD",
        "cik": "0001175454",
        "fillingDate": "2014-09-30",
        "acceptedDate": "2014-09-29 20:00:00",
        "calendarYear": "2014",
        "period": "Q3",
        "netIncome": 95509000,
        "depreciationAndAmortization": 24362000,
        "deferredIncomeTax": -3312000,
        "stockBasedCompensation": 7993000,
        "changeInWorkingCapital": 60458000,
        "accountsReceivables": 59725000,
        "inventory": 0,
        "accountsPayables": 0,
        "otherWorkingCapital": 733000,
        "otherNonCashItems": -25239000,
        "netCashProvidedByOperatingActivities": 159771000,
        "investmentsInPropertyPlantAndEquipment": -6727000,
        "acquisitionsNet": -72069000,
        "purchasesOfInvestments": 0,
        "salesMaturitiesOfInvestments": 0,
        "otherInvestingActivites": 0,
        "netCashUsedForInvestingActivites": -78796000,
        "debtRepayment": -106146000,
        "commonStockIssued": 13645000,
        "commonStockRepurchased": 0,
        "dividendsPaid": 0,
        "otherFinancingActivites": 34526000,
        "netCashUsedProvidedByFinancingActivities": -57975000,
        "effectOfForexChangesOnCash": -16533000,
        "netChangeInCash": 6467000,
        "cashAtEndOfPeriod": 304109000,
        "cashAtBeginningOfPeriod": 297642000,
        "operatingCashFlow": 159771000,
        "capitalExpenditure": -6727000,
        "freeCashFlow": 153044000,
        "link": null,
        "finalLink": null
    },
    {
        "date": "2014-06-30",
        "symbol": "CPAY",
        "reportedCurrency": "USD",
        "cik": "0001175454",
        "fillingDate": "2014-06-30",
        "acceptedDate": "2014-06-29 20:00:00",
        "calendarYear": "2014",
        "period": "Q2",
        "netIncome": 88549000,
        "depreciationAndAmortization": 23082000,
        "deferredIncomeTax": 1429000,
        "stockBasedCompensation": 7687000,
        "changeInWorkingCapital": -21577000,
        "accountsReceivables": -44483000,
        "inventory": 0,
        "accountsPayables": 0,
        "otherWorkingCapital": 22906000,
        "otherNonCashItems": 7057000,
        "netCashProvidedByOperatingActivities": 106227000,
        "investmentsInPropertyPlantAndEquipment": -5968000,
        "acquisitionsNet": -170558000,
        "purchasesOfInvestments": 0,
        "salesMaturitiesOfInvestments": 0,
        "otherInvestingActivites": 0,
        "netCashUsedForInvestingActivites": -176526000,
        "debtRepayment": 76552000,
        "commonStockIssued": 3765000,
        "commonStockRepurchased": 0,
        "dividendsPaid": 0,
        "otherFinancingActivites": 2358000,
        "netCashUsedProvidedByFinancingActivities": 82675000,
        "effectOfForexChangesOnCash": 1892000,
        "netChangeInCash": 14268000,
        "cashAtEndOfPeriod": 297642000,
        "cashAtBeginningOfPeriod": 283374000,
        "operatingCashFlow": 106227000,
        "capitalExpenditure": -5968000,
        "freeCashFlow": 100259000,
        "link": null,
        "finalLink": null
    },
    {
        "date": "2014-03-31",
        "symbol": "CPAY",
        "reportedCurrency": "USD",
        "cik": "0001175454",
        "fillingDate": "2014-03-31",
        "acceptedDate": "2014-03-30 20:00:00",
        "calendarYear": "2014",
        "period": "Q1",
        "netIncome": 75109000,
        "depreciationAndAmortization": 23073000,
        "deferredIncomeTax": 603000,
        "stockBasedCompensation": 10612000,
        "changeInWorkingCapital": -48676000,
        "accountsReceivables": -153184000,
        "inventory": 0,
        "accountsPayables": 0,
        "otherWorkingCapital": 104508000,
        "otherNonCashItems": -9227000,
        "netCashProvidedByOperatingActivities": 51494000,
        "investmentsInPropertyPlantAndEquipment": -5584000,
        "acquisitionsNet": -19292000,
        "purchasesOfInvestments": 0,
        "salesMaturitiesOfInvestments": 0,
        "otherInvestingActivites": 0,
        "netCashUsedForInvestingActivites": -24876000,
        "debtRepayment": -100764000,
        "commonStockIssued": 4512000,
        "commonStockRepurchased": 0,
        "dividendsPaid": 0,
        "otherFinancingActivites": 15359000,
        "netCashUsedProvidedByFinancingActivities": -80893000,
        "effectOfForexChangesOnCash": -456000,
        "netChangeInCash": -54731000,
        "cashAtEndOfPeriod": 283374000,
        "cashAtBeginningOfPeriod": 338105000,
        "operatingCashFlow": 51494000,
        "capitalExpenditure": -5584000,
        "freeCashFlow": 45910000,
        "link": null,
        "finalLink": null
    },
    {
        "date": "2013-12-31",
        "symbol": "CPAY",
        "reportedCurrency": "USD",
        "cik": "0001175454",
        "fillingDate": "2013-12-31",
        "acceptedDate": "2013-12-30 19:00:00",
        "calendarYear": "2013",
        "period": "Q4",
        "netIncome": 68120000,
        "depreciationAndAmortization": 22501000,
        "deferredIncomeTax": -929000,
        "stockBasedCompensation": 14235000,
        "changeInWorkingCapital": 65508000,
        "accountsReceivables": 139362000,
        "inventory": 0,
        "accountsPayables": 0,
        "otherWorkingCapital": -73854000,
        "otherNonCashItems": -1761000,
        "netCashProvidedByOperatingActivities": 167674000,
        "investmentsInPropertyPlantAndEquipment": -5437000,
        "acquisitionsNet": -351372000,
        "purchasesOfInvestments": 0,
        "salesMaturitiesOfInvestments": 0,
        "otherInvestingActivites": 0,
        "netCashUsedForInvestingActivites": -356809000,
        "debtRepayment": 180391000,
        "commonStockIssued": 7638000,
        "commonStockRepurchased": 0,
        "dividendsPaid": 0,
        "otherFinancingActivites": -5909000,
        "netCashUsedProvidedByFinancingActivities": 182120000,
        "effectOfForexChangesOnCash": -569000,
        "netChangeInCash": -7584000,
        "cashAtEndOfPeriod": 338105000,
        "cashAtBeginningOfPeriod": 345689000,
        "operatingCashFlow": 167674000,
        "capitalExpenditure": -5437000,
        "freeCashFlow": 162237000,
        "link": null,
        "finalLink": null
    },
    {
        "date": "2013-09-30",
        "symbol": "CPAY",
        "reportedCurrency": "USD",
        "cik": "0001175454",
        "fillingDate": "2013-09-30",
        "acceptedDate": "2013-09-29 20:00:00",
        "calendarYear": "2013",
        "period": "Q3",
        "netIncome": 78620000,
        "depreciationAndAmortization": 16404000,
        "deferredIncomeTax": -1926000,
        "stockBasedCompensation": 4382000,
        "changeInWorkingCapital": 33595000,
        "accountsReceivables": 6631000,
        "inventory": 0,
        "accountsPayables": 0,
        "otherWorkingCapital": 26964000,
        "otherNonCashItems": -5776000,
        "netCashProvidedByOperatingActivities": 125299000,
        "investmentsInPropertyPlantAndEquipment": -5240000,
        "acquisitionsNet": -220015000,
        "purchasesOfInvestments": 0,
        "salesMaturitiesOfInvestments": 0,
        "otherInvestingActivites": 0,
        "netCashUsedForInvestingActivites": -225255000,
        "debtRepayment": 121012000,
        "commonStockIssued": 10289000,
        "commonStockRepurchased": 0,
        "dividendsPaid": 0,
        "otherFinancingActivites": 12220000,
        "netCashUsedProvidedByFinancingActivities": 143521000,
        "effectOfForexChangesOnCash": 9219000,
        "netChangeInCash": 52784000,
        "cashAtEndOfPeriod": 345689000,
        "cashAtBeginningOfPeriod": 292905000,
        "operatingCashFlow": 125299000,
        "capitalExpenditure": -5240000,
        "freeCashFlow": 120059000,
        "link": null,
        "finalLink": null
    },
    {
        "date": "2013-06-30",
        "symbol": "CPAY",
        "reportedCurrency": "USD",
        "cik": "0001175454",
        "fillingDate": "2013-06-30",
        "acceptedDate": "2013-06-29 20:00:00",
        "calendarYear": "2013",
        "period": "Q2",
        "netIncome": 73099000,
        "depreciationAndAmortization": 14240000,
        "deferredIncomeTax": -1586000,
        "stockBasedCompensation": 3897000,
        "changeInWorkingCapital": 6537000,
        "accountsReceivables": 1485000,
        "inventory": 0,
        "accountsPayables": 0,
        "otherWorkingCapital": 5052000,
        "otherNonCashItems": 215000,
        "netCashProvidedByOperatingActivities": 96402000,
        "investmentsInPropertyPlantAndEquipment": -5346000,
        "acquisitionsNet": -62183000,
        "purchasesOfInvestments": 0,
        "salesMaturitiesOfInvestments": 0,
        "otherInvestingActivites": 0,
        "netCashUsedForInvestingActivites": -67529000,
        "debtRepayment": 33199000,
        "commonStockIssued": 7255000,
        "commonStockRepurchased": 0,
        "dividendsPaid": 0,
        "otherFinancingActivites": 6039000,
        "netCashUsedProvidedByFinancingActivities": 46493000,
        "effectOfForexChangesOnCash": -7074000,
        "netChangeInCash": 68292000,
        "cashAtEndOfPeriod": 292905000,
        "cashAtBeginningOfPeriod": 224613000,
        "operatingCashFlow": 96402000,
        "capitalExpenditure": -5346000,
        "freeCashFlow": 91056000,
        "link": null,
        "finalLink": null
    },
    {
        "date": "2013-03-31",
        "symbol": "CPAY",
        "reportedCurrency": "USD",
        "cik": "0001175454",
        "fillingDate": "2013-03-31",
        "acceptedDate": "2013-03-30 20:00:00",
        "calendarYear": "2013",
        "period": "Q1",
        "netIncome": 64662000,
        "depreciationAndAmortization": 13053000,
        "deferredIncomeTax": -1012000,
        "stockBasedCompensation": 4162000,
        "changeInWorkingCapital": -94748000,
        "accountsReceivables": -192483000,
        "inventory": 0,
        "accountsPayables": 0,
        "otherWorkingCapital": 97735000,
        "otherNonCashItems": 193000,
        "netCashProvidedByOperatingActivities": -13690000,
        "investmentsInPropertyPlantAndEquipment": -4762000,
        "acquisitionsNet": -94773000,
        "purchasesOfInvestments": 0,
        "salesMaturitiesOfInvestments": 0,
        "otherInvestingActivites": 0,
        "netCashUsedForInvestingActivites": -99535000,
        "debtRepayment": 54500000,
        "commonStockIssued": 5256000,
        "commonStockRepurchased": 0,
        "dividendsPaid": 0,
        "otherFinancingActivites": 3835000,
        "netCashUsedProvidedByFinancingActivities": 63591000,
        "effectOfForexChangesOnCash": -9402000,
        "netChangeInCash": -59036000,
        "cashAtEndOfPeriod": 224613000,
        "cashAtBeginningOfPeriod": 283649000,
        "operatingCashFlow": -13690000,
        "capitalExpenditure": -4762000,
        "freeCashFlow": -18452000,
        "link": null,
        "finalLink": null
    }
]